simplefourierfilter.py
simplefourierfilter-0.4.dist-info/.gitignore
simplefourierfilter-0.4.dist-info/LICENSE
simplefourierfilter-0.4.dist-info/METADATA
simplefourierfilter-0.4.dist-info/WHEEL
simplefourierfilter-0.4.dist-info/top_level.txt
simplefourierfilter-0.4.dist-info/RECORD
