Metadata-Version: 2.1
Name: simplefourierfilter
Version: 0.4
Summary: Simple FFT based library for noise reduction
License-File: LICENSE
Requires-Dist: numpy
Requires-Dist: matplotlib
